tapestry/__init__.py
tapestry/base.py
tapestry/base.pyi
tapestry/edge.py
tapestry/edge.pyi
tapestry/engine.py
tapestry/field.py
tapestry/field.pyi
tapestry/node.py
tapestry/node.pyi
tapestry/py.typed
tapestry/query.py
tapestry/query.pyi
tapestry/table.py
tapestry/tokenizer.py
tapestry/utils.py
tapestry_orm-0.0.1.dist-info/WHEEL
tapestry_orm-0.0.1.dist-info/METADATA
tapestry_orm-0.0.1.dist-info/RECORD
