Metadata-Version: 2.3
Name: tapestry-orm
Version: 0.0.1
Summary: A prototype ORM for SurrealDB
Author-email: timothee@obrecht.xyz
License: MIT
Requires-Dist: more-itertools>=10.7.0
Requires-Dist: pydantic>=2.11.7
Requires-Dist: surrealdb>=1.0.6
Requires-Python: >=3.12
